httparse-0.2.1.dist-info/METADATA
httparse-0.2.1.dist-info/WHEEL
httparse-0.2.1.dist-info/license_files/LICENSE.txt
httparse/_httparse.pyi
httparse/_types.py
httparse/py.typed
httparse/__init__.py
httparse/_httparse.abi3.so
httparse-0.2.1.dist-info/RECORD
