Metadata-Version: 2.1
Name: httparse
Version: 0.2.1
Classifier: Development Status :: 3 - Alpha
Classifier: Intended Audience :: Developers
Classifier: License :: OSI Approved :: MIT License
Classifier: Topic :: Software Development
Classifier: Topic :: Software Development :: Libraries
Classifier: Topic :: Software Development :: Libraries :: Python Modules
Requires-Dist: typing-extensions>=3; python_version < '3.8'
License-File: LICENSE.txt
Summary: Push parser for HTTP 1.x
Author: Adrian Garcia Badaracco
License: MIT
Requires-Python: >=3.7
Project-URL: homepage, https://github.com/adriangb/httparse
Project-URL: documentation, https://github.com/adriangb/httparse/README.md
Project-URL: repository, https://github.com/adriangb/httparse
